fresh_useragent
