Metadata-Version: 2.1
Name: fresh-useragent
Version: 1.0.0
Summary: Simple User Agent Generator
Home-page: UNKNOWN
Author: Toyu
Author-email: toyugaming@outlook.com
License: MIT
Keywords: useragent
Platform: UNKNOWN
Classifier: Development Status :: 5 - Production/Stable
Classifier: Intended Audience :: Education
Classifier: Operating System :: Microsoft :: Windows :: Windows 10
Classifier: License :: OSI Approved :: MIT License
Classifier: Programming Language :: Python :: 3
License-File: LICENCE.txt
